{
  "raw_text": "Lirik Lagu L'Arc en Ciel Cureless (Album HEAVENLY) & Terjemahan Bahasa Indonesia\nLirik Lagu L'Arc en Ciel Cureless\nterserak dalam album \nmajor label\nkedua mereka,\nHEAVENLY\n(1995).Â  Cureless diciptakan musiknya oleh tetsu dan \nliriknya oleh Hyde. Lagu ini menjadi track kedelapan dari 10 tracks dalam\nalbum Heavenly. Meskipun tidak menjadi hits seperti And She Said dan Vivid \nColors, tetapi lagu yang berkisah tentang patah hati ini memiliki lirik yang sangat manis khas hyde.\nLirik L'Arc~en~Ciel Cureless\nsama halnya dengan\nSecret Signs\nmemang tidak mendapatkan apresiasi yang lebih populer dibandingkan lagu-lagu lain. Namun kisah romantisnya yang perih, yang menggambarkan 'luka tak tersembuhkan' (sesuai dengan judulnya, cureless), ibarat sisi sebaliknya dari lagu Still I'm With You di album yang sama. Aku lirik dalam Cureless mengenang kekasihnya yang harus berpisah dengan meninggalkan luka masing-masing.\nAku lirik\n, menggambarkan kesia-siaan hidupnya dalam kalimat 'Aku yang tak tahu apa itu cinta, bahkan kehilangan kau juga'.\nBerikut ini\nlirik lagu Cureless\ndan terjemahan dalam bahasa Indonesia, yang sekali lagi menggambarkan keahlian hyde dalam menulis lirik patah hati\n.\nCureless\nlirik: hyde/ lagu: tetsu\nitami o oboete yuku\nGARASU goshi no omoi wa tada mitsumeru dake\nafureru yasashisa o\nmikansei na boku wa dakishimerarenakute\nsaat kugugah kenangan tentang luka,\nmasih saja hanya kuamati rasa yang kusimpan dalam kaca\naku yang tak sempurna ini tak bisa memeluk luapan kelembutan\naishikata o shiranai boku wa anata sae mo nakushi soo\nmuyuubyoo no yoo ni toki o kizamu hari o sagashite mo\nmitsukaranai\naku yang tak tahu apa itu cinta bahkan kehilangan kau juga\nmeski kucari jarum waktu dan memahatnya layaknya mengigau,\ntak kunjung kutemui\nfurete shimaeba togire soo na anata wa setsunakute\notoshita shizuku hiroi atsumete mite mo ai ni wa naranai\njika kusentuh kau yang patah, nanti menyesakkanmu juga\nwalau kucoba kumpulkan titik yang menetes, hal itu tak bisa jadi cinta\nkono yoru tsukamaete mo\nonaji yoo ni ano hito no namae yobenai\nare kara arifureta\nyume ni nemuru yume o mitsuzukete iru yo\nmeski kautelah kupegang malam ini\ntak bisa kusebut nama kekasihku seperti yangÂ  biasanya\ndari sana begitu gampangnya kulanjutkan mimpi\ntidur dalam mimpi\naishikata o shiranai boku wa anata sae mo nakushi soo\nmuyuubyoo no yoo ni toki o kizamu hari o hayamete mo\nsamayotteru\naku yang tak tahu apa itu cinta bahkan kehilangan kau juga\nmeski kupercepat jarum waktu dan memahatnya layaknya mengigau,\nkutetap tersesat\nshiroi toiki ni furuete iru anata o iyasenai\nkareta kono te ga kizutsukete shimau kara\nitami wa kienai\nkutak bisa menyembuhkan engkau yang menggigil dalam putihnya desah\ntangan ini telah mati karenanya akhirnya kuhanya bisa menyakitimu\nlukamu itu takkan bisa lenyap\nfurete shimaeba togire soo na anata wa setsunakute\notoshita shizuku hiroi atsumete mite mo ai ni wa naranai\njika kusentuh kau yang patah, nanti menyesakkanmu juga\nwalau kucoba kumpulkan titik yang menetes, hal itu tak bisa jadi cinta\nshiroi toiki ni furuete iru anata ga setsunakute\nsotto daki yoseta anata no mukoo gawa ni\nano hi no watashi ga yurete kieta\nkutak bisa menyembuhkan engkau yang menggigil dalam putihnya desah\nperlahan, kupeluk erat sisi lain dirimu\naku yang berguncang di hari itu, pun lenyap\nğŸ”— Lihat Asli",
  "parsed_info": {
    "Bio / Profil": {
      "nama": "L'Arc en Ciel",
      "asal": "",
      "genre": "",
      "tahun_aktif": "",
      "deskripsi": ""
    },
    "Diskografi": [
      {
        "judul_album": "HEAVENLY",
        "tahun_rilis": "1995"
      }
    ],
    "Lirik": [
      {
        "judul_lagu": "Cureless",
        "lirik": "itami o oboete yuku\nGARASU goshi no omoi wa tada mitsumeru dake\nafureru yasashisa o\nmikansei na boku wa dakishimerarenakute\nsaat kugugah kenangan tentang luka,\nmasih saja hanya kuamati rasa yang kusimpan dalam kaca\naku yang tak sempurna ini tak bisa memeluk luapan kelembutan\naishikata o shiranai boku wa anata sae mo nakushi soo\nmuyuubyoo no yoo ni toki o kizamu hari o sagashite mo\nmitsukaranai\naku yang tak tahu apa itu cinta bahkan kehilangan kau juga\nmeski kucari jarum waktu dan memahatnya layaknya mengigau,\ntak kunjung kutemui\nfurete shimaeba togire soo na anata wa setsunakute\notoshita shizuku hiroi atsumete mite mo ai ni wa naranai\njika kusentuh kau yang patah, nanti menyesakkanmu juga\nwalau kucoba kumpulkan titik yang menetes, hal itu tak bisa jadi cinta\nkono yoru tsukamaete mo\nonaji yoo ni ano hito no namae yobenai\nare kara arifureta\nyume ni nemuru yume o mitsuzukete iru yo\nmeski kautelah kupegang malam ini\ntak bisa kusebut nama kekasihku seperti yang  biasanya\ndari sana begitu gampangnya kulanjutkan mimpi\ntidur dalam mimpi\naishikata o shiranai boku wa anata sae mo nakushi soo\nmuyuubyoo no yoo ni toki o kizamu hari o hayamete mo\nsamayotteru\naku yang tak tahu apa itu cinta bahkan kehilangan kau juga\nmeski kupercepat jarum waktu dan memahatnya layaknya mengigau,\nkutetap tersesat\nshiroi toiki ni furuete iru anata o iyasenai\nkareta kono te ga kizutsukete shimau kara\nitami wa kienai\nkutak bisa menyembuhkan engkau yang menggigil dalam putihnya desah\ntangan ini telah mati karenanya akhirnya kuhanya bisa menyakitimu\nlukamu itu takkan bisa lenyap\nfurete shimaeba togire soo na anata wa setsunakute\notoshita shizuku hiroi atsumete mite mo ai ni wa naranai\njika kusentuh kau yang patah, nanti menyesakkanmu juga\nwalau kucoba kumpulkan titik yang menetes, hal itu tak bisa jadi cinta\nshiroi toiki ni furuete iru anata ga setsunakute\nsotto daki yoseta anata no mukoo gawa ni\nano hi no watashi ga yurete kieta\nkutak bisa menyembuhkan engkau yang menggigil dalam putihnya desah\nperlahan, kupeluk erat sisi lain dirimu\naku yang berguncang di hari itu, pun lenyap",
        "penulis_lirik": "Hyde",
        "penulis_musik": "Tetsu"
      }
    ]
  },
  "groq_status": "success",
  "groq_error": [],
  "raw_response": "Berikut adalah data yang diambil dari teks tersebut dalam format JSON:\n\n```json\n{\n  \"Bio / Profil\": {\n    \"nama\": \"L'Arc en Ciel\",\n    \"asal\": \"\",\n    \"genre\": \"\",\n    \"tahun_aktif\": \"\",\n    \"deskripsi\": \"\"\n  },\n  \"Diskografi\": [\n    {\n      \"judul_album\": \"HEAVENLY\",\n      \"tahun_rilis\": \"1995\"\n    }\n  ],\n  \"Lirik\": [\n    {\n      \"judul_lagu\": \"Cureless\",\n      \"lirik\": \"itami o oboete yuku\\nGARASU goshi no omoi wa tada mitsumeru dake\\nafureru yasashisa o\\nmikansei na boku wa dakishimerarenakute\\nsaat kugugah kenangan tentang luka,\\nmasih saja hanya kuamati rasa yang kusimpan dalam kaca\\naku yang tak sempurna ini tak bisa memeluk luapan kelembutan\\naishikata o shiranai boku wa anata sae mo nakushi soo\\nmuyuubyoo no yoo ni toki o kizamu hari o sagashite mo\\nmitsukaranai\\naku yang tak tahu apa itu cinta bahkan kehilangan kau juga\\nmeski kucari jarum waktu dan memahatnya layaknya mengigau,\\ntak kunjung kutemui\\nfurete shimaeba togire soo na anata wa setsunakute\\notoshita shizuku hiroi atsumete mite mo ai ni wa naranai\\njika kusentuh kau yang patah, nanti menyesakkanmu juga\\nwalau kucoba kumpulkan titik yang menetes, hal itu tak bisa jadi cinta\\nkono yoru tsukamaete mo\\nonaji yoo ni ano hito no namae yobenai\\nare kara arifureta\\nyume ni nemuru yume o mitsuzukete iru yo\\nmeski kautelah kupegang malam ini\\ntak bisa kusebut nama kekasihku seperti yang  biasanya\\ndari sana begitu gampangnya kulanjutkan mimpi\\ntidur dalam mimpi\\naishikata o shiranai boku wa anata sae mo nakushi soo\\nmuyuubyoo no yoo ni toki o kizamu hari o hayamete mo\\nsamayotteru\\naku yang tak tahu apa itu cinta bahkan kehilangan kau juga\\nmeski kupercepat jarum waktu dan memahatnya layaknya mengigau,\\nkutetap tersesat\\nshiroi toiki ni furuete iru anata o iyasenai\\nkareta kono te ga kizutsukete shimau kara\\nitami wa kienai\\nkutak bisa menyembuhkan engkau yang menggigil dalam putihnya desah\\ntangan ini telah mati karenanya akhirnya kuhanya bisa menyakitimu\\nlukamu itu takkan bisa lenyap\\nfurete shimaeba togire soo na anata wa setsunakute\\notoshita shizuku hiroi atsumete mite mo ai ni wa naranai\\njika kusentuh kau yang patah, nanti menyesakkanmu juga\\nwalau kucoba kumpulkan titik yang menetes, hal itu tak bisa jadi cinta\\nshiroi toiki ni furuete iru anata ga setsunakute\\nsotto daki yoseta anata no mukoo gawa ni\\nano hi no watashi ga yurete kieta\\nkutak bisa menyembuhkan engkau yang menggigil dalam putihnya desah\\nperlahan, kupeluk erat sisi lain dirimu\\naku yang berguncang di hari itu, pun lenyap\",\n      \"penulis_lirik\": \"Hyde\",\n      \"penulis_musik\": \"Tetsu\"\n    }\n  ]\n}\n```"
}